CatKit-0.5.4.dist-info/METADATA
CatKit-0.5.4.dist-info/RECORD
CatKit-0.5.4.dist-info/WHEEL
CatKit-0.5.4.dist-info/dependency_links.txt
CatKit-0.5.4.dist-info/entry_points.txt
CatKit-0.5.4.dist-info/top_level.txt
catkit/__init__.py
catkit/build.py
catkit/enumeration.py
catkit/gratoms.py
catkit/learn.py
catkit/flow/__init__.py
catkit/flow/db.py
catkit/flow/fwase.py
catkit/flow/fwio.py
catkit/flow/laminar.py
catkit/flow/utils.py
catkit/gen/__init__.py
catkit/gen/adsorption.py
catkit/gen/molecules.py
catkit/gen/pathways.py
catkit/gen/route.py
catkit/gen/surface.py
catkit/gen/symmetry.py
catkit/gen/analysis/__init__.py
catkit/gen/analysis/classifier.py
catkit/gen/analysis/matching.py
catkit/gen/utils/__init__.py
catkit/gen/utils/connectivity.py
catkit/gen/utils/coordinates.py
catkit/gen/utils/graph.py
catkit/gen/utils/utilities.py
catkit/gen/utils/vectors.py
catkit/hub/__init__.py
catkit/hub/ase_connect.py
catkit/hub/cathubsqlite.py
catkit/hub/cli.py
catkit/hub/convert_traj.py
catkit/hub/create_user.py
catkit/hub/db2server.py
catkit/hub/db_status.py
catkit/hub/folder2db.py
catkit/hub/folder_check.py
catkit/hub/folderreader.py
catkit/hub/maintain_server.py
catkit/hub/make_folders_template.py
catkit/hub/organize.py
catkit/hub/postgresql.py
catkit/hub/psql_server_connect.py
catkit/hub/query.py
catkit/hub/tools.py
catkit/hub/write_user_spec.py
catkit/hub/ase_tools/__init__.py
catkit/hub/ase_tools/gas_phase_references.py
catkit/pawprint/__init__.py
catkit/pawprint/db.py
catkit/pawprint/generator.py
catkit/pawprint/operations.py
