Metadata-Version: 2.1
Name: CatKit
Version: 0.5.4
Summary: General purpose tools for high-throughput catalysis.
Home-page: https://github.com/SUNCAT-Center/CatKit
Author: Jacob Boes
Author-email: jrboes@stanford.edu
License: GPL-3.0
Platform: UNKNOWN
Classifier: Development Status :: 4 - Beta
Classifier: Intended Audience :: Developers
Classifier: Topic :: Scientific/Engineering :: Chemistry
Classifier: License :: OSI Approved :: GNU General Public License v3 (GPLv3)
Classifier: Programming Language :: Python
Classifier: Programming Language :: Python :: 2
Classifier: Programming Language :: Python :: 2.7
Classifier: Programming Language :: Python :: 3
Classifier: Programming Language :: Python :: 3.5
Classifier: Programming Language :: Python :: 3.6
Requires-Python: >=2.7, !=3.0.*, !=3.1.*, !=3.2.*, !=3.3.*, !=3.4.*, <4
Requires-Dist: ase (>=3.17)
Requires-Dist: cathub (>=0.1.0)
Requires-Dist: numpy (>=1.14)
Requires-Dist: networkx (>=2.1)
Requires-Dist: spglib (>=1.10)
Requires-Dist: scipy (>=0.1)
Requires-Dist: sklearn
Requires-Dist: matplotlib (>=2.2)
Requires-Dist: future (>=0.16)
Requires-Dist: fireworks (>=1.7)
Requires-Dist: sqlalchemy (>=1.2)
Requires-Dist: click (>=6.7)
Requires-Dist: psycopg2-binary (>=2)
Requires-Dist: python-Levenshtein (>=0.12)
Requires-Dist: pathlib2 (>=2.3)
Requires-Dist: tabulate (>=0.8.2)
Requires-Dist: ase (>=3.16.2)
